LICENSE
README.md
setup.cfg
setup.py
define/__init__.py
define/__main__.py
define/array.py
define/base.py
define/constants.py
define/hash.py
define/node.py
define/options.py
define/parent.py
define/tree.py
define_oc.egg-info/PKG-INFO
define_oc.egg-info/SOURCES.txt
define_oc.egg-info/dependency_links.txt
define_oc.egg-info/requires.txt
define_oc.egg-info/top_level.txt
define_oc.egg-info/zip-safe